<annotation verified="yes">
    <folder>Annotation</folder>
    <filename>050lg0sf.png</filename>
    <path>crosswalk-PascalVOC-export/Annotations/050lg0sf.png</path>
    <source>
        <database>Unknown</database>
    </source>
    <size>
        <width>100</width>
        <height>100</height>
        <depth>3</depth>
    </size>
    <segmented>0</segmented>
    <object>
    <name>crosswalk</name>
    <pose>Unspecified</pose>
    <truncated>0</truncated>
    <difficult>0</difficult>
    <bndbox>
        <xmin>0</xmin>
        <ymin>47.83549783549783</ymin>
        <xmax>76.89393939393939</xmax>
        <ymax>63.85281385281385</ymax>
    </bndbox>
</object><object>
    <name>crosswalk</name>
    <pose>Unspecified</pose>
    <truncated>0</truncated>
    <difficult>0</difficult>
    <bndbox>
        <xmin>0</xmin>
        <ymin>77.59740259740259</ymin>
        <xmax>68.3982683982684</xmax>
        <ymax>94.48051948051948</ymax>
    </bndbox>
</object>
</annotation>
