<annotation verified="yes">
    <folder>Annotation</folder>
    <filename>5onWiBcs.png</filename>
    <path>crosswalk-PascalVOC-export/Annotations/5onWiBcs.png</path>
    <source>
        <database>Unknown</database>
    </source>
    <size>
        <width>100</width>
        <height>100</height>
        <depth>3</depth>
    </size>
    <segmented>0</segmented>
    <object>
    <name>crosswalk</name>
    <pose>Unspecified</pose>
    <truncated>0</truncated>
    <difficult>0</difficult>
    <bndbox>
        <xmin>6.4393939393939394</xmin>
        <ymin>53.57142857142857</ymin>
        <xmax>100</xmax>
        <ymax>100</ymax>
    </bndbox>
</object>
</annotation>
